flask_cc_wechat/__init__.py
flask_cc_wechat/auth.py
flask_cc_wechat/menu.py
flask_cc_wechat/message.py
flask_cc_wechat/token.py
flask_cc_wechat-0.1.1.dist-info/METADATA
flask_cc_wechat-0.1.1.dist-info/WHEEL
flask_cc_wechat-0.1.1.dist-info/top_level.txt
flask_cc_wechat-0.1.1.dist-info/zip-safe
flask_cc_wechat-0.1.1.dist-info/RECORD
