Metadata-Version: 2.1
Name: flask-cc-wechat
Version: 0.1.1
Summary: Flask wechat expansion development
Home-page: UNKNOWN
Author: wen
Author-email: w_angzhiwen@163.com
License: BSD
Platform: any
Classifier: Environment :: Web Environment
Classifier: Intended Audience :: Developers
Classifier: License :: OSI Approved :: BSD License
Classifier: Operating System :: OS Independent
Classifier: Programming Language :: Python
Classifier: Topic :: Internet :: WWW/HTTP :: Dynamic Content
Classifier: Topic :: Software Development :: Libraries :: Python Modules
Requires-Dist: Flask
Requires-Dist: requests
